APB_Protocol/rtl/slave.v
module slave (
	input wire clk,
	input wire rst_n,
	input wire psel,
	input wire penable,
	input wire pwrite,
	input wire [4:0] paddr,
	input wire [31:0] pwdata,
	output reg pready,
	output reg [31:0] data
);

reg [1:0] state, next_state;
reg [31:0] memory[31:0];
integer i;
reg [2:0] slave_time;

localparam IDLE = 2'b00;
localparam SETUP = 2'b01;
localparam ACCESS = 2'b10;

always @(posedge clk or negedge rst_n) begin
	if(!rst_n) begin
		state <= IDLE;
	end else begin
		state <= next_state;
	end
end

always @(*) begin
	case (state) 
		IDLE: next_state <= (psel) ? SETUP : IDLE; 
		SETUP: next_state <= (psel && penable) ? ACCESS : SETUP;
		ACCESS: next_state <= IDLE;
	endcase
end

always @(posedge clk or negedge rst_n) begin
	if(!rst_n) begin
		pready <= 1'b0;
		data <= 32'h00000000;
		for(i = 0; i < 32; i = i + 1) begin
			memory[i] <= 32'h00000000;
		end
		slave_time <= 3'b000;
	end else begin
		if(state == ACCESS) begin
			if(slave_time == 3'b100) begin
				if(pwrite) begin
					memory[paddr] <= pwdata;
					pready <= 1'b1;
					data <= 32'h00000000;
				end else begin
					data <= memory[paddr];
					pready <= 1'b1;
				end
				slave_time <= 3'b000;
			end else begin
				slave_time <= slave_time + 1'b1;
			end
		end else begin
			pready <= 1'b0;
		end
	end
end
endmodule

APB_Protocol/rtl/master.v
module master (
	input wire clk,
	input wire rst_n,
	input wire [4:0] paddr,
	input wire [31:0] pwdata,
	input wire pwrite_in,
	input wire pready,
	output reg psel,
	output reg penable,
	output reg pwrite,
	output reg [4:0] paddr_out,
	output reg [31:0] pwdata_out
);

reg [1:0] state, next_state;
localparam IDLE = 2'b00;
localparam SETUP = 2'b01;
localparam ACCESS = 2'b10;
localparam WAIT = 2'b11;

always @(posedge clk or negedge rst_n) begin
	if(!rst_n) begin
		state <= IDLE;
	end else begin
		state <= next_state;
	end
end

always @(*) begin
	case (state)
		IDLE: begin
			next_state <=  SETUP; 
		end
		SETUP: begin
			next_state <= ACCESS;
		end
		ACCESS: begin
			next_state <= (pready) ? IDLE : WAIT;
		end
		WAIT: begin
			next_state <= (pready) ? IDLE : WAIT;
		end
	endcase
end

always @(posedge clk or negedge rst_n) begin
	if(!rst_n) begin
		psel <= 1'b0;
		penable <= 1'b0;
		pwrite <= 1'b0;
		paddr_out = 5'h00;
		pwdata_out = 32'h00000000;
	end else begin
		case (state) 
			IDLE: begin
				psel <= 1'b0;
				penable <= 1'b0;
				pwrite <= 1'b0;
			end
			SETUP: begin
				psel <= 1'b1;
				pwrite <= pwrite_in;
			end
			ACCESS: begin
				penable <= 1'b1;
				if(!pready) begin
					paddr_out <= paddr;
					pwdata_out <= pwdata;
				end 
			end
			WAIT: begin	
				if(!pready) begin
					paddr_out <= paddr;
					pwdata_out <= pwdata;
				end
			end
		endcase
	end
end	

endmodule

APB_Protocol/rtl/top.v
module top(
	input wire clk,
	input wire rst_n,
	input wire [4:0] paddr,
	input wire [31:0] pwdata,
	input wire pwrite_in,
	output reg [31:0] data,
	output reg pready
);

wire psel, penable, pwrite, pready_internal;
wire [4:0] paddr_internal;
wire [31:0] pwdata_internal, data_out;

master ic1 (
	.clk(clk),
	.rst_n(rst_n),
	.paddr(paddr),
	.pwdata(pwdata),
	.pwrite_in(pwrite_in),
	.pready(pready_internal),
	.psel(psel),
	.penable(penable),
	.pwrite(pwrite),
	.paddr_out(paddr_internal),
	.pwdata_out(pwdata_internal)
);

slave ic2 (
	.clk(clk),
	.rst_n(rst_n),
	.psel(psel),
	.penable(penable),
	.pwrite(pwrite),
	.paddr(paddr_internal),
	.pwdata(pwdata_internal),
	.pready(pready_internal),
	.data(data_out)
);

always @(*) begin
	pready <= pready_internal;
	data <= data_out;
end

endmodule

APB_Protocol/tb/test_bench.v
`timescale 1ns/1ps
module test_bench;
	reg clk;
    	reg rst_n;
	reg [4:0] paddr;
	reg [31:0] pwdata;
	reg pwrite_in;
	wire [31:0] data;
	wire pready;

	top dut(.*);

	integer i;
	reg [31:0] rad_data;

	initial begin
		clk = 0;
		forever #5 clk = ~clk;
	end

	task verify;
		input [31:0] exp_data;
		begin
			$display("At time: %t,rst_n = 1'b%b, paddr = 5'h%h, pwdata = 32'h%h, pwrite_in = 1'b%b", $time, rst_n, paddr, pwdata, pwrite_in);
			if(data == exp_data) begin
				$display("-------------------------------------------------------------------------------------------------------------------------------");
				$display("PASSED: Expected data: 32'h%h, Got data: 32'h%h", exp_data, data); 
				$display("-------------------------------------------------------------------------------------------------------------------------------");
			end else begin
				$display("-------------------------------------------------------------------------------------------------------------------------------");
				$display("FAILED: Expected data: 32'h%h, Got data: 32'h%h", exp_data, data); 
				$display("-------------------------------------------------------------------------------------------------------------------------------");
			end
		end
	endtask

	task setup;
		input [4:0] exp_paddr;
		input [31:0] exp_pwdata;
		input exp_pwrite_in;
		begin
			paddr = exp_paddr;
			pwdata = exp_pwdata;
			pwrite_in = exp_pwrite_in;
			wait(pready);
			wait(!pready);
		end
	endtask

	initial begin
		$dumpfile("test_bench.vcd");
		$dumpvars(0, test_bench);

		$display("-------------------------------------------------------------------------------------------------------------------------------");
		$display("-------------------------------------------TESTBENCH FOR APB PROTOCOL----------------------------------------------------------"); 
		$display("-------------------------------------------------------------------------------------------------------------------------------");

		rst_n = 0;
		@(posedge clk);
		verify(32'h00000000);
		
		rst_n = 1;
		@(posedge clk);
		setup(5'h0f, 32'hffff0000, 1);
		verify(32'h00000000);
		setup(5'h0f, 32'hffff0000,0);
		verify(32'hffff0000);
		@(posedge clk);
		setup(5'h04, 32'hffffffff, 1);
		verify(32'h00000000);
		setup(5'h04, 32'hffffffff,0);
		verify(32'hffffffff);
		for (i = 0; i < 32; i = i + 1) begin
			rad_data = $urandom % 10000;
			setup(i, rad_data, 1);
			setup(i, rad_data, 0);
			verify(rad_data);
		end
		#100;
		$finish;

	end
endmodule

APB_Protocol/sim/test_bench.vcd
$date
	Sun Jan 26 23:26:06 2025
$end
$version
	Icarus Verilog
$end
$timescale
	1ps
$end
$scope module test_bench $end
$var wire 1 ! pready $end
$var wire 32 " data [31:0] $end
$var reg 1 # clk $end
$var reg 5 $ paddr [4:0] $end
$var reg 32 % pwdata [31:0] $end
$var reg 1 & pwrite_in $end
$var reg 32 ' rad_data [31:0] $end
$var reg 1 ( rst_n $end
$var integer 32 ) i [31:0] $end
$scope module dut $end
$var wire 1 # clk $end
$var wire 5 * paddr [4:0] $end
$var wire 32 + pwdata [31:0] $end
$var wire 1 & pwrite_in $end
$var wire 1 ( rst_n $end
$var wire 1 , pwrite $end
$var wire 32 - pwdata_internal [31:0] $end
$var wire 1 . psel $end
$var wire 1 / pready_internal $end
$var wire 1 0 penable $end
$var wire 5 1 paddr_internal [4:0] $end
$var wire 32 2 data_out [31:0] $end
$var reg 32 3 data [31:0] $end
$var reg 1 ! pready $end
$scope module ic1 $end
$var wire 1 # clk $end
$var wire 5 4 paddr [4:0] $end
$var wire 32 5 pwdata [31:0] $end
$var wire 1 & pwrite_in $end
$var wire 1 ( rst_n $end
$var wire 1 / pready $end
$var parameter 2 6 ACCESS $end
$var parameter 2 7 IDLE $end
$var parameter 2 8 SETUP $end
$var parameter 2 9 WAIT $end
$var reg 2 : next_state [1:0] $end
$var reg 5 ; paddr_out [4:0] $end
$var reg 1 0 penable $end
$var reg 1 . psel $end
$var reg 32 < pwdata_out [31:0] $end
$var reg 1 , pwrite $end
$var reg 2 = state [1:0] $end
$upscope $end
$scope module ic2 $end
$var wire 1 # clk $end
$var wire 5 > paddr [4:0] $end
$var wire 1 0 penable $end
$var wire 1 . psel $end
$var wire 32 ? pwdata [31:0] $end
$var wire 1 , pwrite $end
$var wire 1 ( rst_n $end
$var parameter 2 @ ACCESS $end
$var parameter 2 A IDLE $end
$var parameter 2 B SETUP $end
$var reg 32 C data [31:0] $end
$var reg 2 D next_state [1:0] $end
$var reg 1 / pready $end
$var reg 3 E slave_time [2:0] $end
$var reg 2 F state [1:0] $end
$var integer 32 G i [31:0] $end
$upscope $end
$upscope $end
$scope task setup $end
$var reg 5 H exp_paddr [4:0] $end
$var reg 32 I exp_pwdata [31:0] $end
$var reg 1 J exp_pwrite_in $end
$upscope $end
$scope task verify $end
$var reg 32 K exp_data [31:0] $end
$upscope $end
$upscope $end
$enddefinitions $end
$comment Show the parameter values. $end
$dumpall
b1 B
b0 A
b10 @
b11 9
b1 8
b0 7
b10 6
$end
#0
$dumpvars
bx K
xJ
bx I
bx H
b100000 G
b0 F
b0 E
b0 D
b0 C
b0 ?
b0 >
b0 =
b0 <
b0 ;
b1 :
bx 5
bx 4
b0 3
b0 2
b0 1
00
0/
0.
b0 -
0,
bx +
bx *
bx )
0(
bx '
x&
bx %
bx $
0#
b0 "
0!
$end
#5000
b10 :
b1 =
1(
b0 K
1#
#10000
0#
#15000
b11 :
b1 D
b10 =
1,
1.
1&
b11111111111111110000000000000000 %
b11111111111111110000000000000000 +
b11111111111111110000000000000000 5
b1111 $
b1111 *
b1111 4
1J
b11111111111111110000000000000000 I
b1111 H
1#
#20000
0#
#25000
b10 D
b1 F
b11111111111111110000000000000000 -
b11111111111111110000000000000000 <
b11111111111111110000000000000000 ?
b1111 1
b1111 ;
b1111 >
10
b11 =
1#
#30000
0#
#35000
b0 D
b10 F
1#
#40000
0#
#45000
b1 D
b1 E
b0 F
1#
#50000
0#
#55000
b10 D
b1 F
1#
#60000
0#
#65000
b0 D
b10 F
1#
#70000
0#
#75000
b1 D
b0 F
b10 E
1#
#80000
0#
#85000
b10 D
b1 F
1#
#90000
0#
#95000
b0 D
b10 F
1#
#100000
0#
#105000
b1 D
b11 E
b0 F
1#
#110000
0#
#115000
b10 D
b1 F
1#
#120000
0#
#125000
b0 D
b10 F
1#
#130000
0#
#135000
b1 D
b0 F
b100 E
1#
#140000
0#
#145000
b10 D
b1 F
1#
#150000
0#
#155000
b0 D
b10 F
1#
#160000
0#
#165000
1!
b0 :
b1 D
b0 E
1/
b0 F
1#
#170000
0#
#175000
0&
0J
b10 D
0!
b1 :
b0 =
b1 F
0/
1#
#180000
0#
#185000
b0 D
b10 :
b10 F
0,
00
0.
b1 =
1#
#190000
0#
#195000
b11 :
b1 D
b10 =
1.
b0 F
b1 E
1#
#200000
0#
#205000
b10 D
b1 F
10
b11 =
1#
#210000
0#
#215000
b0 D
b10 F
1#
#220000
0#
#225000
b1 D
b10 E
b0 F
1#
#230000
0#
#235000
b10 D
b1 F
1#
#240000
0#
#245000
b0 D
b10 F
1#
#250000
0#
#255000
b1 D
b0 F
b11 E
1#
#260000
0#
#265000
b10 D
b1 F
1#
#270000
0#
#275000
b0 D
b10 F
1#
#280000
0#
#285000
b1 D
b100 E
b0 F
1#
#290000
0#
#295000
b10 D
b1 F
1#
#300000
0#
#305000
b0 D
b10 F
1#
#310000
0#
#315000
b1 D
b0 :
b11111111111111110000000000000000 "
b11111111111111110000000000000000 3
1!
b0 F
b0 E
1/
b11111111111111110000000000000000 2
b11111111111111110000000000000000 C
1#
#320000
0#
#325000
b11111111111111110000000000000000 K
0!
b10 D
b1 :
0/
b1 F
b0 =
1#
#330000
0#
#335000
b10 :
b0 D
b1 =
00
0.
b10 F
1&
b11111111111111111111111111111111 %
b11111111111111111111111111111111 +
b11111111111111111111111111111111 5
b100 $
b100 *
b100 4
1J
b11111111111111111111111111111111 I
b100 H
1#
#340000
0#
#345000
b1 D
b11 :
b1 E
b0 F
1,
1.
b10 =
1#
#350000
0#
#355000
b10 D
b11 =
b11111111111111111111111111111111 -
b11111111111111111111111111111111 <
b11111111111111111111111111111111 ?
b100 1
b100 ;
b100 >
10
b1 F
1#
#360000
0#
#365000
b0 D
b10 F
1#
#370000
0#
#375000
b1 D
b0 F
b10 E
1#
#380000
0#
#385000
b10 D
b1 F
1#
#390000
0#
#395000
b0 D
b10 F
1#
#400000
0#
#405000
b1 D
b11 E
b0 F
1#
#410000
0#
#415000
b10 D
b1 F
1#
#420000
0#
#425000
b0 D
b10 F
1#
#430000
0#
#435000
b1 D
b0 F
b100 E
1#
#440000
0#
#445000
b10 D
b1 F
1#
#450000
0#
#455000
b0 D
b10 F
1#
#460000
0#
#465000
b0 "
b0 3
1!
b0 :
b1 D
b0 E
b0 2
b0 C
1/
b0 F
1#
#470000
0#
#475000
0&
0J
b0 K
b10 D
0!
b1 :
b0 =
b1 F
0/
1#
#480000
0#
#485000
b0 D
b10 :
b10 F
0,
00
0.
b1 =
1#
#490000
0#
#495000
b11 :
b1 D
b10 =
1.
b0 F
b1 E
1#
#500000
0#
#505000
b10 D
b1 F
10
b11 =
1#
#510000
0#
#515000
b0 D
b10 F
1#
#520000
0#
#525000
b1 D
b10 E
b0 F
1#
#530000
0#
#535000
b10 D
b1 F
1#
#540000
0#
#545000
b0 D
b10 F
1#
#550000
0#
#555000
b1 D
b0 F
b11 E
1#
#560000
0#
#565000
b10 D
b1 F
1#
#570000
0#
#575000
b0 D
b10 F
1#
#580000
0#
#585000
b1 D
b100 E
b0 F
1#
#590000
0#
#595000
b10 D
b1 F
1#
#600000
0#
#605000
b0 D
b10 F
1#
#610000
0#
#615000
b1 D
b0 :
b11111111111111111111111111111111 "
b11111111111111111111111111111111 3
1!
b0 F
b0 E
1/
b11111111111111111111111111111111 2
b11111111111111111111111111111111 C
1#
#620000
0#
#625000
1&
b110101000100 %
b110101000100 +
b110101000100 5
b0 $
b0 *
b0 4
1J
b110101000100 I
b0 H
b110101000100 '
b0 )
b11111111111111111111111111111111 K
0!
b10 D
b1 :
0/
b1 F
b0 =
1#
#630000
0#
#635000
b10 :
b0 D
b1 =
00
0.
b10 F
1#
#640000
0#
#645000
b1 D
b11 :
b1 E
b0 F
1,
1.
b10 =
1#
#650000
0#
#655000
b10 D
b11 =
b110101000100 -
b110101000100 <
b110101000100 ?
b0 1
b0 ;
b0 >
10
b1 F
1#
#660000
0#
#665000
b0 D
b10 F
1#
#670000
0#
#675000
b1 D
b0 F
b10 E
1#
#680000
0#
#685000
b10 D
b1 F
1#
#690000
0#
#695000
b0 D
b10 F
1#
#700000
0#
#705000
b1 D
b11 E
b0 F
1#
#710000
0#
#715000
b10 D
b1 F
1#
#720000
0#
#725000
b0 D
b10 F
1#
#730000
0#
#735000
b1 D
b0 F
b100 E
1#
#740000
0#
#745000
b10 D
b1 F
1#
#750000
0#
#755000
b0 D
b10 F
1#
#760000
0#
#765000
b0 "
b0 3
1!
b0 :
b1 D
b0 E
b0 2
b0 C
1/
b0 F
1#
#770000
0#
#775000
0&
0J
b10 D
0!
b1 :
b0 =
b1 F
0/
1#
#780000
0#
#785000
b0 D
b10 :
b10 F
0,
00
0.
b1 =
1#
#790000
0#
#795000
b11 :
b1 D
b10 =
1.
b0 F
b1 E
1#
#800000
0#
#805000
b10 D
b1 F
10
b11 =
1#
#810000
0#
#815000
b0 D
b10 F
1#
#820000
0#
#825000
b1 D
b10 E
b0 F
1#
#830000
0#
#835000
b10 D
b1 F
1#
#840000
0#
#845000
b0 D
b10 F
1#
#850000
0#
#855000
b1 D
b0 F
b11 E
1#
#860000
0#
#865000
b10 D
b1 F
1#
#870000
0#
#875000
b0 D
b10 F
1#
#880000
0#
#885000
b1 D
b100 E
b0 F
1#
#890000
0#
#895000
b10 D
b1 F
1#
#900000
0#
#905000
b0 D
b10 F
1#
#910000
0#
#915000
b1 D
b0 :
b110101000100 "
b110101000100 3
1!
b0 F
b0 E
1/
b110101000100 2
b110101000100 C
1#
#920000
0#
#925000
1&
b1000101100001 %
b1000101100001 +
b1000101100001 5
b1 $
b1 *
b1 4
1J
b1000101100001 I
b1 H
b1000101100001 '
b1 )
b110101000100 K
0!
b10 D
b1 :
0/
b1 F
b0 =
1#
#930000
0#
#935000
b10 :
b0 D
b1 =
00
0.
b10 F
1#
#940000
0#
#945000
b1 D
b11 :
b1 E
b0 F
1,
1.
b10 =
1#
#950000
0#
#955000
b10 D
b11 =
b1000101100001 -
b1000101100001 <
b1000101100001 ?
b1 1
b1 ;
b1 >
10
b1 F
1#
#960000
0#
#965000
b0 D
b10 F
1#
#970000
0#
#975000
b1 D
b0 F
b10 E
1#
#980000
0#
#985000
b10 D
b1 F
1#
#990000
0#
#995000
b0 D
b10 F
1#
#1000000
0#
#1005000
b1 D
b11 E
b0 F
1#
#1010000
0#
#1015000
b10 D
b1 F
1#
#1020000
0#
#1025000
b0 D
b10 F
1#
#1030000
0#
#1035000
b1 D
b0 F
b100 E
1#
#1040000
0#
#1045000
b10 D
b1 F
1#
#1050000
0#
#1055000
b0 D
b10 F
1#
#1060000
0#
#1065000
b0 "
b0 3
1!
b0 :
b1 D
b0 E
b0 2
b0 C
1/
b0 F
1#
#1070000
0#
#1075000
0&
0J
b10 D
0!
b1 :
b0 =
b1 F
0/
1#
#1080000
0#
#1085000
b0 D
b10 :
b10 F
0,
00
0.
b1 =
1#
#1090000
0#
#1095000
b11 :
b1 D
b10 =
1.
b0 F
b1 E
1#
#1100000
0#
#1105000
b10 D
b1 F
10
b11 =
1#
#1110000
0#
#1115000
b0 D
b10 F
1#
#1120000
0#
#1125000
b1 D
b10 E
b0 F
1#
#1130000
0#
#1135000
b10 D
b1 F
1#
#1140000
0#
#1145000
b0 D
b10 F
1#
#1150000
0#
#1155000
b1 D
b0 F
b11 E
1#
#1160000
0#
#1165000
b10 D
b1 F
1#
#1170000
0#
#1175000
b0 D
b10 F
1#
#1180000
0#
#1185000
b1 D
b100 E
b0 F
1#
#1190000
0#
#1195000
b10 D
b1 F
1#
#1200000
0#
#1205000
b0 D
b10 F
1#
#1210000
0#
#1215000
b1 D
b0 :
b1000101100001 "
b1000101100001 3
1!
b0 F
b0 E
1/
b1000101100001 2
b1000101100001 C
1#
#1220000
0#
#1225000
1&
b1000100111001 %
b1000100111001 +
b1000100111001 5
b10 $
b10 *
b10 4
1J
b1000100111001 I
b10 H
b1000100111001 '
b10 )
b1000101100001 K
0!
b10 D
b1 :
0/
b1 F
b0 =
1#
#1230000
0#
#1235000
b10 :
b0 D
b1 =
00
0.
b10 F
1#
#1240000
0#
#1245000
b1 D
b11 :
b1 E
b0 F
1,
1.
b10 =
1#
#1250000
0#
#1255000
b10 D
b11 =
b1000100111001 -
b1000100111001 <
b1000100111001 ?
b10 1
b10 ;
b10 >
10
b1 F
1#
#1260000
0#
#1265000
b0 D
b10 F
1#
#1270000
0#
#1275000
b1 D
b0 F
b10 E
1#
#1280000
0#
#1285000
b10 D
b1 F
1#
#1290000
0#
#1295000
b0 D
b10 F
1#
#1300000
0#
#1305000
b1 D
b11 E
b0 F
1#
#1310000
0#
#1315000
b10 D
b1 F
1#
#1320000
0#
#1325000
b0 D
b10 F
1#
#1330000
0#
#1335000
b1 D
b0 F
b100 E
1#
#1340000
0#
#1345000
b10 D
b1 F
1#
#1350000
0#
#1355000
b0 D
b10 F
1#
#1360000
0#
#1365000
b0 "
b0 3
1!
b0 :
b1 D
b0 E
b0 2
b0 C
1/
b0 F
1#
#1370000
0#
#1375000
0&
0J
b10 D
0!
b1 :
b0 =
b1 F
0/
1#
#1380000
0#
#1385000
b0 D
b10 :
b10 F
0,
00
0.
b1 =
1#
#1390000
0#
#1395000
b11 :
b1 D
b10 =
1.
b0 F
b1 E
1#
#1400000
0#
#1405000
b10 D
b1 F
10
b11 =
1#
#1410000
0#
#1415000
b0 D
b10 F
1#
#1420000
0#
#1425000
b1 D
b10 E
b0 F
1#
#1430000
0#
#1435000
b10 D
b1 F
1#
#1440000
0#
#1445000
b0 D
b10 F
1#
#1450000
0#
#1455000
b1 D
b0 F
b11 E
1#
#1460000
0#
#1465000
b10 D
b1 F
1#
#1470000
0#
#1475000
b0 D
b10 F
1#
#1480000
0#
#1485000
b1 D
b100 E
b0 F
1#
#1490000
0#
#1495000
b10 D
b1 F
1#
#1500000
0#
#1505000
b0 D
b10 F
1#
#1510000
0#
#1515000
b1 D
b0 :
b1000100111001 "
b1000100111001 3
1!
b0 F
b0 E
1/
b1000100111001 2
b1000100111001 C
1#
#1520000
0#
#1525000
1&
b1000011110011 %
b1000011110011 +
b1000011110011 5
b11 $
b11 *
b11 4
1J
b1000011110011 I
b11 H
b1000011110011 '
b11 )
b1000100111001 K
0!
b10 D
b1 :
0/
b1 F
b0 =
1#
#1530000
0#
#1535000
b10 :
b0 D
b1 =
00
0.
b10 F
1#
#1540000
0#
#1545000
b1 D
b11 :
b1 E
b0 F
1,
1.
b10 =
1#
#1550000
0#
#1555000
b10 D
b11 =
b1000011110011 -
b1000011110011 <
b1000011110011 ?
b11 1
b11 ;
b11 >
10
b1 F
1#
#1560000
0#
#1565000
b0 D
b10 F
1#
#1570000
0#
#1575000
b1 D
b0 F
b10 E
1#
#1580000
0#
#1585000
b10 D
b1 F
1#
#1590000
0#
#1595000
b0 D
b10 F
1#
#1600000
0#
#1605000
b1 D
b11 E
b0 F
1#
#1610000
0#
#1615000
b10 D
b1 F
1#
#1620000
0#
#1625000
b0 D
b10 F
1#
#1630000
0#
#1635000
b1 D
b0 F
b100 E
1#
#1640000
0#
#1645000
b10 D
b1 F
1#
#1650000
0#
#1655000
b0 D
b10 F
1#
#1660000
0#
#1665000
b0 "
b0 3
1!
b0 :
b1 D
b0 E
b0 2
b0 C
1/
b0 F
1#
#1670000
0#
#1675000
0&
0J
b10 D
0!
b1 :
b0 =
b1 F
0/
1#
#1680000
0#
#1685000
b0 D
b10 :
b10 F
0,
00
0.
b1 =
1#
#1690000
0#
#1695000
b11 :
b1 D
b10 =
1.
b0 F
b1 E
1#
#1700000
0#
#1705000
b10 D
b1 F
10
b11 =
1#
#1710000
0#
#1715000
b0 D
b10 F
1#
#1720000
0#
#1725000
b1 D
b10 E
b0 F
1#
#1730000
0#
#1735000
b10 D
b1 F
1#
#1740000
0#
#1745000
b0 D
b10 F
1#
#1750000
0#
#1755000
b1 D
b0 F
b11 E
1#
#1760000
0#
#1765000
b10 D
b1 F
1#
#1770000
0#
#1775000
b0 D
b10 F
1#
#1780000
0#
#1785000
b1 D
b100 E
b0 F
1#
#1790000
0#
#1795000
b10 D
b1 F
1#
#1800000
0#
#1805000
b0 D
b10 F
1#
#1810000
0#
#1815000
b1 D
b0 :
b1000011110011 "
b1000011110011 3
1!
b0 F
b0 E
1/
b1000011110011 2
b1000011110011 C
1#
#1820000
0#
#1825000
1&
b101000101101 %
b101000101101 +
b101000101101 5
b100 $
b100 *
b100 4
1J
b101000101101 I
b100 H
b101000101101 '
b100 )
b1000011110011 K
0!
b10 D
b1 :
0/
b1 F
b0 =
1#
#1830000
0#
#1835000
b10 :
b0 D
b1 =
00
0.
b10 F
1#
#1840000
0#
#1845000
b1 D
b11 :
b1 E
b0 F
1,
1.
b10 =
1#
#1850000
0#
#1855000
b10 D
b11 =
b101000101101 -
b101000101101 <
b101000101101 ?
b100 1
b100 ;
b100 >
10
b1 F
1#
#1860000
0#
#1865000
b0 D
b10 F
1#
#1870000
0#
#1875000
b1 D
b0 F
b10 E
1#
#1880000
0#
#1885000
b10 D
b1 F
1#
#1890000
0#
#1895000
b0 D
b10 F
1#
#1900000
0#
#1905000
b1 D
b11 E
b0 F
1#
#1910000
0#
#1915000
b10 D
b1 F
1#
#1920000
0#
#1925000
b0 D
b10 F
1#
#1930000
0#
#1935000
b1 D
b0 F
b100 E
1#
#1940000
0#
#1945000
b10 D
b1 F
1#
#1950000
0#
#1955000
b0 D
b10 F
1#
#1960000
0#
#1965000
b0 "
b0 3
1!
b0 :
b1 D
b0 E
b0 2
b0 C
1/
b0 F
1#
#1970000
0#
#1975000
0&
0J
b10 D
0!
b1 :
b0 =
b1 F
0/
1#
#1980000
0#
#1985000
b0 D
b10 :
b10 F
0,
00
0.
b1 =
1#
#1990000
0#
#1995000
b11 :
b1 D
b10 =
1.
b0 F
b1 E
1#
#2000000
0#
#2005000
b10 D
b1 F
10
b11 =
1#
#2010000
0#
#2015000
b0 D
b10 F
1#
#2020000
0#
#2025000
b1 D
b10 E
b0 F
1#
#2030000
0#
#2035000
b10 D
b1 F
1#
#2040000
0#
#2045000
b0 D
b10 F
1#
#2050000
0#
#2055000
b1 D
b0 F
b11 E
1#
#2060000
0#
#2065000
b10 D
b1 F
1#
#2070000
0#
#2075000
b0 D
b10 F
1#
#2080000
0#
#2085000
b1 D
b100 E
b0 F
1#
#2090000
0#
#2095000
b10 D
b1 F
1#
#2100000
0#
#2105000
b0 D
b10 F
1#
#2110000
0#
#2115000
b1 D
b0 :
b101000101101 "
b101000101101 3
1!
b0 F
b0 E
1/
b101000101101 2
b101000101101 C
1#
#2120000
0#
#2125000
1&
b101 $
b101 *
b101 4
1J
b101 H
b101 )
b101000101101 K
0!
b10 D
b1 :
0/
b1 F
b0 =
1#
#2130000
0#
#2135000
b10 :
b0 D
b1 =
00
0.
b10 F
1#
#2140000
0#
#2145000
b1 D
b11 :
b1 E
b0 F
1,
1.
b10 =
1#
#2150000
0#
#2155000
b10 D
b11 =
b101 1
b101 ;
b101 >
10
b1 F
1#
#2160000
0#
#2165000
b0 D
b10 F
1#
#2170000
0#
#2175000
b1 D
b0 F
b10 E
1#
#2180000
0#
#2185000
b10 D
b1 F
1#
#2190000
0#
#2195000
b0 D
b10 F
1#
#2200000
0#
#2205000
b1 D
b11 E
b0 F
1#
#2210000
0#
#2215000
b10 D
b1 F
1#
#2220000
0#
#2225000
b0 D
b10 F
1#
#2230000
0#
#2235000
b1 D
b0 F
b100 E
1#
#2240000
0#
#2245000
b10 D
b1 F
1#
#2250000
0#
#2255000
b0 D
b10 F
1#
#2260000
0#
#2265000
b0 "
b0 3
1!
b0 :
b1 D
b0 E
b0 2
b0 C
1/
b0 F
1#
#2270000
0#
#2275000
0&
0J
b10 D
0!
b1 :
b0 =
b1 F
0/
1#
#2280000
0#
#2285000
b0 D
b10 :
b10 F
0,
00
0.
b1 =
1#
#2290000
0#
#2295000
b11 :
b1 D
b10 =
1.
b0 F
b1 E
1#
#2300000
0#
#2305000
b10 D
b1 F
10
b11 =
1#
#2310000
0#
#2315000
b0 D
b10 F
1#
#2320000
0#
#2325000
b1 D
b10 E
b0 F
1#
#2330000
0#
#2335000
b10 D
b1 F
1#
#2340000
0#
#2345000
b0 D
b10 F
1#
#2350000
0#
#2355000
b1 D
b0 F
b11 E
1#
#2360000
0#
#2365000
b10 D
b1 F
1#
#2370000
0#
#2375000
b0 D
b10 F
1#
#2380000
0#
#2385000
b1 D
b100 E
b0 F
1#
#2390000
0#
#2395000
b10 D
b1 F
1#
#2400000
0#
#2405000
b0 D
b10 F
1#
#2410000
0#
#2415000
b1 D
b0 :
b101000101101 "
b101000101101 3
1!
b0 F
b0 E
1/
b101000101101 2
b101000101101 C
1#
#2420000
0#
#2425000
1&
b10000111100101 %
b10000111100101 +
b10000111100101 5
b110 $
b110 *
b110 4
1J
b10000111100101 I
b110 H
b10000111100101 '
b110 )
0!
b10 D
b1 :
0/
b1 F
b0 =
1#
#2430000
0#
#2435000
b10 :
b0 D
b1 =
00
0.
b10 F
1#
#2440000
0#
#2445000
b1 D
b11 :
b1 E
b0 F
1,
1.
b10 =
1#
#2450000
0#
#2455000
b10 D
b11 =
b10000111100101 -
b10000111100101 <
b10000111100101 ?
b110 1
b110 ;
b110 >
10
b1 F
1#
#2460000
0#
#2465000
b0 D
b10 F
1#
#2470000
0#
#2475000
b1 D
b0 F
b10 E
1#
#2480000
0#
#2485000
b10 D
b1 F
1#
#2490000
0#
#2495000
b0 D
b10 F
1#
#2500000
0#
#2505000
b1 D
b11 E
b0 F
1#
#2510000
0#
#2515000
b10 D
b1 F
1#
#2520000
0#
#2525000
b0 D
b10 F
1#
#2530000
0#
#2535000
b1 D
b0 F
b100 E
1#
#2540000
0#
#2545000
b10 D
b1 F
1#
#2550000
0#
#2555000
b0 D
b10 F
1#
#2560000
0#
#2565000
b0 "
b0 3
1!
b0 :
b1 D
b0 E
b0 2
b0 C
1/
b0 F
1#
#2570000
0#
#2575000
0&
0J
b10 D
0!
b1 :
b0 =
b1 F
0/
1#
#2580000
0#
#2585000
b0 D
b10 :
b10 F
0,
00
0.
b1 =
1#
#2590000
0#
#2595000
b11 :
b1 D
b10 =
1.
b0 F
b1 E
1#
#2600000
0#
#2605000
b10 D
b1 F
10
b11 =
1#
#2610000
0#
#2615000
b0 D
b10 F
1#
#2620000
0#
#2625000
b1 D
b10 E
b0 F
1#
#2630000
0#
#2635000
b10 D
b1 F
1#
#2640000
0#
#2645000
b0 D
b10 F
1#
#2650000
0#
#2655000
b1 D
b0 F
b11 E
1#
#2660000
0#
#2665000
b10 D
b1 F
1#
#2670000
0#
#2675000
b0 D
b10 F
1#
#2680000
0#
#2685000
b1 D
b100 E
b0 F
1#
#2690000
0#
#2695000
b10 D
b1 F
1#
#2700000
0#
#2705000
b0 D
b10 F
1#
#2710000
0#
#2715000
b1 D
b0 :
b10000111100101 "
b10000111100101 3
1!
b0 F
b0 E
1/
b10000111100101 2
b10000111100101 C
1#
#2720000
0#
#2725000
1&
b110110010 %
b110110010 +
b110110010 5
b111 $
b111 *
b111 4
1J
b110110010 I
b111 H
b110110010 '
b111 )
b10000111100101 K
0!
b10 D
b1 :
0/
b1 F
b0 =
1#
#2730000
0#
#2735000
b10 :
b0 D
b1 =
00
0.
b10 F
1#
#2740000
0#
#2745000
b1 D
b11 :
b1 E
b0 F
1,
1.
b10 =
1#
#2750000
0#
#2755000
b10 D
b11 =
b110110010 -
b110110010 <
b110110010 ?
b111 1
b111 ;
b111 >
10
b1 F
1#
#2760000
0#
#2765000
b0 D
b10 F
1#
#2770000
0#
#2775000
b1 D
b0 F
b10 E
1#
#2780000
0#
#2785000
b10 D
b1 F
1#
#2790000
0#
#2795000
b0 D
b10 F
1#
#2800000
0#
